skill_manager_treeshell-0.1.9.dist-info/licenses/LICENSE
skillmanager_treeshell/__init__.py
skillmanager_treeshell/dashboard_operations.py
skillmanager_treeshell/configs/dev_agent_config.json
skillmanager_treeshell/configs/dev_agent_shortcuts.json
skillmanager_treeshell/configs/dev_agent_zone_config.json
skillmanager_treeshell/configs/dev_base_config.json
skillmanager_treeshell/configs/dev_base_shortcuts.json
skillmanager_treeshell/configs/dev_base_zone_config.json
skillmanager_treeshell/configs/dev_user_config.json
skillmanager_treeshell/configs/dev_user_shortcuts.json
skillmanager_treeshell/configs/dev_user_zone_config.json
skillmanager_treeshell/configs/nav_config.json
skillmanager_treeshell/configs/system_agent_config.json
skillmanager_treeshell/configs/system_agent_shortcuts.json
skillmanager_treeshell/configs/system_agent_zone_config.json
skillmanager_treeshell/configs/system_base_config.json
skillmanager_treeshell/configs/system_base_shortcuts.json
skillmanager_treeshell/configs/system_base_zone_config.json
skillmanager_treeshell/configs/system_user_config.json
skillmanager_treeshell/configs/system_user_shortcuts.json
skillmanager_treeshell/configs/system_user_zone_config.json
skillmanager_treeshell/configs/families/system_dashboard_family.json
skillmanager_treeshell/configs/families/system_family.json
skillmanager_treeshell/configs/families/system_hud_family.json
skillmanager_treeshell/configs/families/system_meta_family.json
skillmanager_treeshell/mcp_server/__init__.py
skillmanager_treeshell/mcp_server/agent_server.py
skillmanager_treeshell/mcp_server/user_server.py
skill_manager_treeshell-0.1.9.dist-info/METADATA
skill_manager_treeshell-0.1.9.dist-info/WHEEL
skill_manager_treeshell-0.1.9.dist-info/entry_points.txt
skill_manager_treeshell-0.1.9.dist-info/top_level.txt
skill_manager_treeshell-0.1.9.dist-info/RECORD
