Metadata-Version: 2.4
Name: skill-manager-treeshell
Version: 0.1.9
Summary: Skill Manager TreeShell MCP - Three-tier skill architecture for compound intelligence
Author: TreeShell Developer
Author-email: Isaac Wright <sancovp@gmail.com>
License-Expression: LicenseRef-GPBL-1.0
Project-URL: Homepage, https://github.com/sancovp/skill-manager-treeshell
Project-URL: Repository, https://github.com/sancovp/skill-manager-treeshell
Project-URL: Issues, https://github.com/sancovp/skill-manager-treeshell/issues
Keywords: mcp,treeshell,skills,claude,ai,compound-intelligence
Classifier: Development Status :: 4 - Beta
Classifier: Intended Audience :: Developers
Classifier: Programming Language :: Python :: 3
Classifier: Programming Language :: Python :: 3.10
Classifier: Programming Language :: Python :: 3.11
Classifier: Programming Language :: Python :: 3.12
Requires-Python: >=3.8
License-File: LICENSE
Requires-Dist: heaven-tree-repl>=0.1.0
Requires-Dist: skill-manager-mcp>=0.1.3
Requires-Dist: mcp>=1.0.0
Dynamic: author
Dynamic: license-file
Dynamic: requires-python
